dagger/__init__.py
dagger/dag/__init__.py
dagger/dag/dag.py
dagger/dag/topological_sort.py
dagger/data_structures/__init__.py
dagger/data_structures/frozen_mapping.py
dagger/dsl/__init__.py
dagger/dsl/build.py
dagger/dsl/context.py
dagger/dsl/dsl.py
dagger/dsl/node_invocation_recorder.py
dagger/dsl/node_invocations.py
dagger/dsl/node_output_key_usage.py
dagger/dsl/node_output_partition_fan_in.py
dagger/dsl/node_output_partition_usage.py
dagger/dsl/node_output_property_usage.py
dagger/dsl/node_output_reference.py
dagger/dsl/node_output_serializer.py
dagger/dsl/node_output_usage.py
dagger/dsl/parameter_usage.py
dagger/input/__init__.py
dagger/input/from_node_output.py
dagger/input/from_param.py
dagger/input/protocol.py
dagger/input/validators.py
dagger/output/__init__.py
dagger/output/from_key.py
dagger/output/from_property.py
dagger/output/from_return_value.py
dagger/output/protocol.py
dagger/output/validators.py
dagger/runtime/argo/__init__.py
dagger/runtime/argo/cron.py
dagger/runtime/argo/cron_workflow_spec.py
dagger/runtime/argo/extra_spec_options.py
dagger/runtime/argo/metadata.py
dagger/runtime/argo/v1alpha1.py
dagger/runtime/argo/workflow.py
dagger/runtime/argo/workflow_spec.py
dagger/runtime/cli/__init__.py
dagger/runtime/cli/cli.py
dagger/runtime/cli/invoke_with_locations.py
dagger/runtime/cli/locations.py
dagger/runtime/cli/nested_nodes.py
dagger/runtime/local/__init__.py
dagger/runtime/local/dag.py
dagger/runtime/local/invoke.py
dagger/runtime/local/output.py
dagger/runtime/local/task.py
dagger/runtime/local/types.py
dagger/serializer/__init__.py
dagger/serializer/as_json.py
dagger/serializer/as_pickle.py
dagger/serializer/errors.py
dagger/serializer/protocol.py
dagger/task/__init__.py
dagger/task/task.py
py_dagger-0.4.2.dist-info/LICENSE
py_dagger-0.4.2.dist-info/WHEEL
py_dagger-0.4.2.dist-info/METADATA
py_dagger-0.4.2.dist-info/RECORD
