Metadata-Version: 2.1
Name: py-dagger
Version: 0.4.2
Summary: Define sophisticated data pipelines with Python and run them on different distributed systems (such as Argo Workflows).
Home-page: https://github.com/larribas/dagger
License: Apache-2.0
Keywords: argo-workflows,data-engineering,data-pipelines,data-science
Author: larribas
Author-email: lorenzo.s.arribas@gmail.com
Requires-Python: >=3.8,<4.0
Classifier: Development Status :: 5 - Production/Stable
Classifier: Intended Audience :: Developers
Classifier: License :: OSI Approved :: Apache Software License
Classifier: Natural Language :: English
Classifier: Programming Language :: Python :: 3
Classifier: Programming Language :: Python :: 3 :: Only
Classifier: Programming Language :: Python :: 3.8
Classifier: Programming Language :: Python :: 3.9
Classifier: Topic :: Software Development :: Build Tools
Project-URL: Documentation, https://larribas.me/dagger
Project-URL: Repository, https://github.com/larribas/dagger
